capture_it/__init__.py
capture_it/_cap_summary.py
capture_it/_captures.py
capture_it/_clp.py
capture_it/_command.py
capture_it/_conn.py
capture_it/_detection.py
capture_it/_exec_device.py
capture_it/common.py
capture_it/executions.py
capture_it/gui.py
capture_it/forms/__init__.py
capture_it/forms/common_to_all.py
capture_it/forms/cred.py
capture_it/forms/custom.py
capture_it/forms/exec_common.py
capture_it/forms/exec_individual.py
capture_it/forms/exec_quick_show.py
capture_it/forms/options.py
capture_it-0.1.3.dist-info/LICENSE
capture_it-0.1.3.dist-info/METADATA
capture_it-0.1.3.dist-info/WHEEL
capture_it-0.1.3.dist-info/top_level.txt
capture_it-0.1.3.dist-info/RECORD
