Metadata-Version: 2.1
Name: capture-it
Version: 0.1.3
Summary: Networking Device show output|Config capture and parsing utility
Home-page: https://github.com/aliasgar1978/capture_it
Author: ALIASGAR - ALI
Author-email: aholo2000@gmail.com
Classifier: Programming Language :: Python :: 3
Classifier: License :: OSI Approved :: MIT License
Classifier: Operating System :: OS Independent
Requires-Python: >=3.7
License-File: LICENSE
Requires-Dist: nettoolkit >0.1.1
Requires-Dist: nettoolkit-common
Requires-Dist: nettoolkit-db
Requires-Dist: paramiko
Requires-Dist: netmiko
Requires-Dist: pandas
Requires-Dist: ntc-templates
